inversion_tools/new_reader.py
personal_research_tools-0.0.2.dist-info/METADATA
personal_research_tools-0.0.2.dist-info/WHEEL
personal_research_tools-0.0.2.dist-info/top_level.txt
personal_research_tools-0.0.2.dist-info/RECORD
