Metadata-Version: 2.4
Name: Personal_research_tools
Version: 0.0.2
Summary: A package containing all my research tools not for anyone else
Home-page: https://github.com/Anthony904175/personal_research_tools.git
Author: Anthony R. Osborne
Author-email: anthony.r.osborne@pm.me
License: GNU3.0
Requires-Python: >=3.8
Dynamic: author
Dynamic: author-email
Dynamic: description
Dynamic: description-content-type
Dynamic: home-page
Dynamic: license
Dynamic: requires-python
Dynamic: summary
